LICENSE
MANIFEST.in
README.rst
setup.py
mail1/__init__.py
mail1/mail1.py
mail1/test_mail1.py
mail1.egg-info/PKG-INFO
mail1.egg-info/SOURCES.txt
mail1.egg-info/dependency_links.txt
mail1.egg-info/entry_points.txt
mail1.egg-info/top_level.txt