Metadata-Version: 1.0
Name: mail1
Version: 4.1.0
Summary: mail1 is an API to send emails in a single call
Home-page: http://pypi.python.org/pypi/mail1/
Author: Michel Casabianca
Author-email: casa@sweetohm.net
License: Apache Software License
Platform: UNKNOWN
